pdcp/__init__.py
pdcp/custom_types.py
pdcp/job.py
pdcp/utils.py
pdcp-1.2.0.dist-info/LICENSE
pdcp-1.2.0.dist-info/METADATA
pdcp-1.2.0.dist-info/WHEEL
pdcp-1.2.0.dist-info/RECORD
