Metadata-Version: 2.3
Name: pdcp
Version: 1.2.0
Summary: Pythonic DCP(Bifrost2) Wrapper
License: MIT
Author: Sebastian Vega
Author-email: sebasvega4604@gmail.com
Requires-Python: >=3.10
Classifier: License :: OSI Approved :: MIT License
Classifier: Programming Language :: Python :: 3
Classifier: Programming Language :: Python :: 3.10
Classifier: Programming Language :: Python :: 3.11
Classifier: Programming Language :: Python :: 3.12
Classifier: Programming Language :: Python :: 3.13
Requires-Dist: dcp (>=3.2.1,<4.0.0)
Requires-Dist: rich (>=14.0.0,<15.0.0)
